glowpython/__init__.py
glowpython/base.py
glowpython/fortran.cpython-39-darwin.so
glowpython/plots.py
glowpython/version.py
glowpython/data/ephoto_xn2.dat
glowpython/data/ephoto_xo.dat
glowpython/data/ephoto_xo2.dat
glowpython/data/snoem_eof.dat
glowpython/data/ssflux_euvac.dat
glowpython/data/ssflux_hint.dat
glowpython/data/iri90/ccir11.asc
glowpython/data/iri90/ccir12.asc
glowpython/data/iri90/ccir13.asc
glowpython/data/iri90/ccir14.asc
glowpython/data/iri90/ccir15.asc
glowpython/data/iri90/ccir16.asc
glowpython/data/iri90/ccir17.asc
glowpython/data/iri90/ccir18.asc
glowpython/data/iri90/ccir19.asc
glowpython/data/iri90/ccir20.asc
glowpython/data/iri90/ccir21.asc
glowpython/data/iri90/ccir22.asc
glowpython/data/iri90/ursi11.asc
glowpython/data/iri90/ursi12.asc
glowpython/data/iri90/ursi13.asc
glowpython/data/iri90/ursi14.asc
glowpython/data/iri90/ursi15.asc
glowpython/data/iri90/ursi16.asc
glowpython/data/iri90/ursi17.asc
glowpython/data/iri90/ursi18.asc
glowpython/data/iri90/ursi19.asc
glowpython/data/iri90/ursi20.asc
glowpython/data/iri90/ursi21.asc
glowpython/data/iri90/ursi22.asc
glowpython-3.0.0.data/scripts/Maxwellian.py
glowpython-3.0.0.data/scripts/NoPrecipitation.py
src/glowpython/__init__.py
src/glowpython/base.py
src/glowpython/plots.py
src/glowpython/version.py
glowpython-3.0.0.dist-info/LICENSE
glowpython-3.0.0.dist-info/METADATA
glowpython-3.0.0.dist-info/WHEEL
glowpython-3.0.0.dist-info/top_level.txt
glowpython-3.0.0.dist-info/RECORD
