Metadata-Version: 2.1
Name: glowpython
Version: 3.0.0
Summary: Python bindings for NCAR GLOW model
Home-page: https://github.com/sunipkm/glowpython
Author: Sunip K. Mukherjee,George Geddes, Ph.D.
Author-email: sunipkmukherjee@gmail.com
License-File: LICENSE
Requires-Dist: numpy (>=1.10)
Requires-Dist: xarray
Requires-Dist: geomagdata
